piveilance/__init__.py
piveilance/_version.py
piveilance/app.py
piveilance/components.py
piveilance/config.py
piveilance/layoutManager.py
piveilance/messaging.py
piveilance/repository.py
piveilance/util.py
piveilance/resources/Qt5Core.dll
piveilance/resources/__init__.py
piveilance/resources/default_config.yaml
piveilance/resources/logger_config.yaml
piveilance/resources/styles.qss
piveilance/resources/__pycache__/__init__.cpython-36.pyc
piveilance/resources/image/data.gif
piveilance/resources/image/ent.jpg
piveilance/resources/image/icon.ico
piveilance/resources/image/offline.gif
piveilance/resources/image/offline_big.gif
test/__init__.py
test/test_config.py
test/test_imanip.py
piveilance-2.0.19.dist-info/METADATA
piveilance-2.0.19.dist-info/WHEEL
piveilance-2.0.19.dist-info/entry_points.txt
piveilance-2.0.19.dist-info/top_level.txt
piveilance-2.0.19.dist-info/RECORD
