Metadata-Version: 2.1
Name: piveilance
Version: 2.0.19
Summary: PiCam Surveilance App
Home-page: https://github.com/vossenv/piveilance
Maintainer: Danimae Vossen
Maintainer-email: vossen.dm@gmail.com
License: MIT
Platform: UNKNOWN
Requires-Dist: click
Requires-Dist: requests
Requires-Dist: python-dateutil
Requires-Dist: click-default-group
Requires-Dist: pyyaml
Requires-Dist: pyqt5 ; sys_platform=="win32"
Requires-Dist: pyqt5-sip ; sys_platform=="win32"
Provides-Extra: setup
Requires-Dist: pyinstaller ; extra == 'setup'
Requires-Dist: wheel ; extra == 'setup'
Requires-Dist: twine ; extra == 'setup'
